README.md
setup.cfg
setup.py
INCV/NationalCodeValidation.py
INCV/__init__.py
INCV.egg-info/PKG-INFO
INCV.egg-info/SOURCES.txt
INCV.egg-info/dependency_links.txt
INCV.egg-info/top_level.txt