Metadata-Version: 1.0
Name: INCV
Version: 0.1.1
Summary: This package validates the national code of Iranians
Home-page: https://github.com/majidazizian/incv
Author: Majid Azizian
Author-email: your.email@domain.com
License: MIT
Platform: UNKNOWN
